magCalibration/__init__.py
magCalibration/magCalib.py
magCalibration/scripts/__init__.py
magCalibration/scripts/aliasPS.py
magCalibration/scripts/angles.py
magCalibration/scripts/angles_choose.py
magCalibration/scripts/autoGold.py
magCalibration/scripts/calcStats.py
magCalibration/scripts/convertMRC.py
magCalibration/scripts/correctAniso.py
magCalibration/scripts/getUserAngles.py
magCalibration/scripts/getUserBoxes.py
magCalibration/scripts/makeAllNWPS_MTF.py
magCalibration/scripts/makeAllNWPS_blank.py
magCalibration/scripts/makeAllNWPS_ignore.py
magCalibration/scripts/makeBlankNPS_ra.py
magCalibration/scripts/makeIgnoreNPS_ra.py
magCalibration/scripts/makeImageNPS_ra.py
magCalibration/scripts/makeOneUnwhitenedPS.py
magCalibration/scripts/makeUnwhitenedPSAll.py
magCalibration/scripts/measurePxAllAngles.py
magCalibration/scripts/measurePxAvg.py
magCalibration/scripts/measurePxAvg_fit.py
magCalibration/scripts/measurePxAvg_max.py
magCalibration/scripts/show_FFT.py
magCalibration/scripts/smooth_choose.py
magCalEM-1.3.6.dist-info/LICENSE.txt
magCalEM-1.3.6.dist-info/METADATA
magCalEM-1.3.6.dist-info/WHEEL
magCalEM-1.3.6.dist-info/top_level.txt
magCalEM-1.3.6.dist-info/RECORD
