Metadata-Version: 2.1
Name: magCalEM
Version: 1.3.6
Summary: A program to calibrate the pixel size of cryoEM data
Author: Joshua L. Dickerson
Author-email: jdickerson@mrc-lmb.cam.ac.uk
License: MIT
Requires-Python: >=3.6
License-File: LICENSE.txt
Requires-Dist: PyQt5
Requires-Dist: numpy
Requires-Dist: mrcfile
Requires-Dist: opencv-python
Requires-Dist: matplotlib
Requires-Dist: scipy
Requires-Dist: numba
Requires-Dist: psutil
Requires-Dist: scikit-image
Requires-Dist: pandas
Requires-Dist: lmfit
